devwer/__init__.py
devwer/metrics.py
devwer/normalizer.py
devwer-0.0.3.dist-info/METADATA
devwer-0.0.3.dist-info/WHEEL
devwer-0.0.3.dist-info/top_level.txt
devwer-0.0.3.dist-info/RECORD
