Metadata-Version: 2.4
Name: devwer
Version: 0.0.3
Summary: A Word Error Rate (WER) evaluation Metrics Calculator for Devnagari (Nepali) language.
Home-page: https://github.com/kiranpantha/DevWordErrorRate
Author: Kiran Pantha
Author-email: info@kiranpantha.com.np
Classifier: Programming Language :: Python :: 3
Classifier: License :: OSI Approved :: MIT License
Classifier: Operating System :: OS Independent
Requires-Python: >=3.6
Requires-Dist: numpy>=1.18.0
Requires-Dist: python-Levenshtein
Dynamic: author
Dynamic: author-email
Dynamic: classifier
Dynamic: description
Dynamic: description-content-type
Dynamic: home-page
Dynamic: requires-dist
Dynamic: requires-python
Dynamic: summary
